shifter.v
module shifter(
    input  [31:0] A,
    input  [4:0]  shamt,
    input  [2:0]  sel,   
    output reg [31:0] Y
);
always @(*) begin
    case (sel)
        3'd0: Y = A << shamt;
        3'd1: Y = A >> shamt;
        3'd2: Y = $signed(A) >>> shamt;
        3'd3: Y = (A << shamt) | (A >> (32-shamt));
        3'd4: Y = (A >> shamt) | (A << (32-shamt));
        default: Y = 32'b0;
    endcase
end
endmodule

rtl/logic_unit.v
module logic_unit(
    input  [31:0] A,
    input  [31:0] B,
    input  [1:0]  sel,  
    output reg [31:0] Y
);
always @(*) begin
    case (sel)
        2'b00: Y = A & B;
        2'b01: Y = A | B;
        2'b10: Y = A ^ B;
        default: Y = 32'b0;
    endcase
end
endmodule

ripple_adder.v
module ripple_adder(
    input [31:0] A,
    input [31:0] B,
    input Cin,
    output [31:0] Sum,
    output Cout);
    wire [31:0]carry;
    
    assign {carry[0],Sum[0]} = A[0]+B[0]+ Cin;
    genvar i;
    generate
        for(i=1;i<32;i=i+1)
        begin:fa_loop
           assign {carry[i], Sum[i]} = A[i] + B[i] + carry[i-1];
        end
        
    endgenerate
    assign Cout = carry[31];
endmodule

rtl/alu.v
module alu(
    input  [31:0] A,
    input  [31:0] B,
    input         cin,
    input  [4:0]  shamt,
    input  [4:0]  opcode,
    output reg [31:0] result,
    output reg        carryout,
    output reg        overflow,
    output reg        zero
);

    // opcode map
    localparam OP_ADD  = 5'd0;
    localparam OP_SUB  = 5'd1;
    localparam OP_AND  = 5'd2;
    localparam OP_OR   = 5'd3;
    localparam OP_XOR  = 5'd4;
    localparam OP_SLL  = 5'd5;
    localparam OP_SRL  = 5'd6;
    localparam OP_SRA  = 5'd7;
    localparam OP_ROTL = 5'd8;
    localparam OP_ROTR = 5'd9;
    localparam OP_SLT  = 5'd10;

    // internal wires
    wire [31:0] adder_sum;
    wire        adder_cout;
    wire [31:0] logic_out;
    wire [31:0] shifter_y;

    reg  [1:0]  logic_sel;
    reg  [2:0]  shifter_sel;

    wire [31:0] adder_B   = (opcode == OP_SUB) ? ~B : B;
    wire        adder_cin = (opcode == OP_SUB) ? 1'b1 : cin;

    // ripple adder
    ripple_adder u_ripple_adder (
        .A(A),
        .B(adder_B),
        .Cin(adder_cin),
        .Sum(adder_sum),
        .Cout(adder_cout)
    );

    // logic unit
    logic_unit u_logic_unit (
        .A(A),
        .B(B),
        .sel(logic_sel),
        .Y(logic_out)
    );

    // shifter
    shifter u_shifter (
        .A(A),
        .shamt(shamt),
        .sel(shifter_sel),
        .Y(shifter_y)
    );

    // ALU control + result select
    always @(*) begin
        result       = 32'b0;
        carryout     = 1'b0;
        overflow     = 1'b0;
        zero         = 1'b0;
        logic_sel    = 2'b00;
        shifter_sel  = 3'b000;

        case (opcode)

            OP_ADD: begin
                result   = adder_sum;
                carryout = adder_cout;
                overflow = (A[31] & B[31] & ~result[31]) |
                           (~A[31] & ~B[31] & result[31]);
            end

            OP_SUB: begin
                result   = adder_sum;
                carryout = adder_cout;
                overflow = (A[31] & ~B[31] & ~result[31]) |
                           (~A[31] &  B[31] &  result[31]);
            end

            OP_AND: begin
                logic_sel = 2'b00;
                result    = logic_out;
            end

            OP_OR: begin
                logic_sel = 2'b01;
                result    = logic_out;
            end

            OP_XOR: begin
                logic_sel = 2'b10;
                result    = logic_out;
            end

            OP_SLL:  begin shifter_sel = 3'd0; result = shifter_y; end
            OP_SRL:  begin shifter_sel = 3'd1; result = shifter_y; end
            OP_SRA:  begin shifter_sel = 3'd2; result = shifter_y; end
            OP_ROTL: begin shifter_sel = 3'd3; result = shifter_y; end
            OP_ROTR: begin shifter_sel = 3'd4; result = shifter_y; end

            OP_SLT: begin
                result = {31'b0, ($signed(A) < $signed(B))};
            end

            default: result = 32'b0;
        endcase

        zero = (result == 32'b0);
    end
endmodule

alu_tb.v

`timescale 1ns/1ps

module alu_selfcheck_tb;

   
    reg  [31:0] A;
    reg  [31:0] B;
    reg         cin;
    reg  [4:0]  shamt;
    reg  [4:0]  opcode;

    wire [31:0] result;
    wire        carryout;
    wire        overflow;
    wire        zero;

    
    alu uut (
        .A(A),
        .B(B),
        .cin(cin),
        .shamt(shamt),
        .opcode(opcode),
        .result(result),
        .carryout(carryout),
        .overflow(overflow),
        .zero(zero)
    );

    
    localparam OP_ADD  = 5'd0;
    localparam OP_SUB  = 5'd1;
    localparam OP_AND  = 5'd2;
    localparam OP_OR   = 5'd3;
    localparam OP_XOR  = 5'd4;
    localparam OP_SLL  = 5'd5;
    localparam OP_SRL  = 5'd6;
    localparam OP_SRA  = 5'd7;
    localparam OP_ROTL = 5'd8;
    localparam OP_ROTR = 5'd9;
    localparam OP_SLT  = 5'd10;

    
    reg  [31:0] expected_result;
    reg         expected_carry;
    reg         expected_overflow;
    reg         expected_zero;
    reg  [31:0] r;
    reg  [32:0] tmp_result;  // one way to resolve carry error by using 33 bit temperoray result 

    
    integer idx;
    integer passcount;
    integer failcount;

    function [31:0] rotl;
        input [31:0] v;
        input [4:0] s;
        begin 
            rotl = (v << s) | (v >> (32-s));
        end
    endfunction

   
    function [31:0] rotr;
        input [31:0] v;
        input [4:0] s;
        begin 
            rotr = (v >> s) | (v << (32-s));
        end
    endfunction

   
    task expected;
        input [31:0] ta;
        input [31:0] tb;
        input tcin;
        input [4:0]  tshamt;
        input [4:0]  top;
        begin

          
            expected_result   = 32'b0;
            expected_carry    = 1'b0;
            expected_overflow = 1'b0;
            expected_zero     = 1'b0;

            case(top)

                OP_ADD: begin
                    {expected_carry, expected_result} = ta + tb + tcin;
                    expected_overflow = (ta[31] & tb[31] & ~expected_result[31]) |
                                        (~ta[31] & ~tb[31] & expected_result[31]);
                end

               
                OP_SUB: begin
                    tmp_result = {1'b0, ta} + {1'b0, ~tb} + 33'b1;
                    expected_carry = tmp_result[32];
                    expected_result = tmp_result[31:0];
                    expected_overflow = (ta[31] & ~tb[31] & ~expected_result[31]) |
                                        (~ta[31] & tb[31] & expected_result[31]);
                end

               
                OP_AND: begin
                    expected_result = ta & tb;
                end
                
                OP_OR: begin
                    expected_result = ta | tb;
                end

                OP_XOR: begin
                    expected_result = ta ^ tb;
                end

                
                OP_ROTL: begin 
                    expected_result = rotl(ta, tshamt);
                end

                OP_ROTR: begin
                    expected_result = rotr(ta, tshamt);
                end

                
                OP_SLL: begin
                    expected_result = ta << tshamt;
                end

                OP_SRL: begin
                    expected_result = ta >> tshamt;
                end

                OP_SLT: begin
                    expected_result = {31'b0, ($signed(ta) < $signed(tb))};
                end

                OP_SRA: begin
                    expected_result = $signed(ta) >>> tshamt;
                end

               
                default: begin
                    expected_result = 32'b0;
                end

            endcase

            
            expected_zero = (expected_result == 32'b0);
        end
    endtask

    
    task apply_and_check(input [31:0] ta, input [31:0] tb, input tcin, input [4:0] tshamt, input [4:0] top);
        begin
            
            A = ta; 
            B = tb; 
            cin = tcin; 
            shamt = tshamt; 
            opcode = top;
            #5;
            expected(ta, tb, tcin, tshamt, top);

            
            if(result != expected_result) begin
                $display("FAIL: time=%0t OP=%0d shamt=%0d A=%0h B=%0h | RESULT: GOT=%0h EXP=%0h",
                    $time, top, tshamt, ta, tb, result, expected_result);
                failcount = failcount + 1;
            end
           
            else if(carryout != expected_carry) begin
                $display("FAIL: time=%0t OP=%0d shamt=%0d A=%0h B=%0h | CARRYOUT: GOT=%0h EXP=%0h",
                    $time, top, tshamt, ta, tb, carryout, expected_carry);
                failcount = failcount + 1;
            end
          
            else if(overflow != expected_overflow) begin
                $display("FAIL: time=%0t OP=%0d shamt=%0d A=%0h B=%0h | OVERFLOW: GOT=%0h EXP=%0h",
                    $time, top, tshamt, ta, tb, overflow, expected_overflow);
                failcount = failcount + 1;
            end
            
            else if(zero != expected_zero) begin
                $display("FAIL: time=%0t OP=%0d shamt=%0d A=%0h B=%0h | ZERO: GOT=%0h EXP=%0h",
                    $time, top, tshamt, ta, tb, zero, expected_zero);
                failcount = failcount + 1;
            end
            
            else begin
                passcount = passcount + 1;
            end
        end
    endtask

    
    initial begin
       
        $dumpfile("alu_selfcheck_tb.vcd");
        $dumpvars(0, alu_selfcheck_tb);

       
        failcount = 0;
        passcount = 0;

        
        apply_and_check(32'd15, 32'd10, 1'b0, 5'd0, OP_ADD);
        apply_and_check(32'hFFFFFFFF, 32'h00000001, 1'b0, 5'd0, OP_ADD);
        apply_and_check(32'h40000000, 32'h40000000, 1'b0, 5'd0, OP_ADD);

       
        apply_and_check(32'd20, 32'd5, 1'b0, 5'd0, OP_SUB);
        apply_and_check(32'h7FFFFFFF, 32'hFFFFFFFF, 1'b0, 5'd0, OP_SUB);

        
        apply_and_check(32'hA5A5A5A5, 32'h0F0F0F0F, 1'b0, 5'd0, OP_AND);
        apply_and_check(32'hA5A5A5A5, 32'h0F0F0F0F, 1'b0, 5'd0, OP_OR);
        apply_and_check(32'hA5A5A5A5, 32'hFFFF0000, 1'b0, 5'd0, OP_XOR);

        
        apply_and_check(32'h0000FFFF, 32'd0, 1'b0, 5'd8, OP_SLL);
        apply_and_check(32'hFF000000, 32'd0, 1'b0, 5'd8, OP_SRL);
        apply_and_check(32'h80000000, 32'd0, 1'b0, 5'd4, OP_SRA);

        
        apply_and_check(32'h12345678, 32'd0, 1'b0, 5'd8, OP_ROTL);
        apply_and_check(32'h12345678, 32'd0, 1'b0, 5'd8, OP_ROTR);

       
        apply_and_check(32'hFFFFFFFF, 32'd1, 1'b0, 5'd0, OP_SLT);
        apply_and_check(32'd0, 32'd0, 1'b0, 5'd0, OP_ADD);

        for (idx = 0; idx < 200; idx = idx + 1) begin
            r = $random;
            if ((r % 11) == OP_SUB) begin
                
                apply_and_check($random, $random, 1'b0, r[4:0], OP_SUB); 
            end else begin
                
                apply_and_check($random, $random, $random & 1, r[4:0], r % 11);
            end
            #10;
        end

       
        $display("\n");
        $display("========================================");
        $display("SELF-CHECK COMPLETE");
        $display("========================================");
        $display("PASSED: %0d tests", passcount);
        $display("FAILED: %0d tests", failcount);
        $display("========================================");
        
        if (failcount != 0) begin
            $display("One or more tests FAILED.");
        end else begin
            $display("All tests PASSED!");
        end
        $display("========================================\n");

        $finish;
    end

endmodule

sim/alu_selfcheck_tb.vcd
$date
	Sun Dec 14 13:24:25 2025
$end
$version
	Icarus Verilog
$end
$timescale
	1ps
$end
$scope module alu_selfcheck_tb $end
$var wire 1 ! zero $end
$var wire 32 " result [31:0] $end
$var wire 1 # overflow $end
$var wire 1 $ carryout $end
$var parameter 5 % OP_ADD $end
$var parameter 5 & OP_AND $end
$var parameter 5 ' OP_OR $end
$var parameter 5 ( OP_ROTL $end
$var parameter 5 ) OP_ROTR $end
$var parameter 5 * OP_SLL $end
$var parameter 5 + OP_SLT $end
$var parameter 5 , OP_SRA $end
$var parameter 5 - OP_SRL $end
$var parameter 5 . OP_SUB $end
$var parameter 5 / OP_XOR $end
$var reg 32 0 A [31:0] $end
$var reg 32 1 B [31:0] $end
$var reg 1 2 cin $end
$var reg 1 3 expected_carry $end
$var reg 1 4 expected_overflow $end
$var reg 32 5 expected_result [31:0] $end
$var reg 1 6 expected_zero $end
$var reg 5 7 opcode [4:0] $end
$var reg 32 8 r [31:0] $end
$var reg 5 9 shamt [4:0] $end
$var reg 33 : tmp_result [32:0] $end
$var integer 32 ; failcount [31:0] $end
$var integer 32 < idx [31:0] $end
$var integer 32 = passcount [31:0] $end
$scope function rotl $end
$var reg 5 > s [4:0] $end
$var reg 32 ? v [31:0] $end
$upscope $end
$scope function rotr $end
$var reg 5 @ s [4:0] $end
$var reg 32 A v [31:0] $end
$upscope $end
$scope module uut $end
$var wire 32 B A [31:0] $end
$var wire 32 C B [31:0] $end
$var wire 1 2 cin $end
$var wire 5 D opcode [4:0] $end
$var wire 5 E shamt [4:0] $end
$var wire 32 F shifter_y [31:0] $end
$var wire 32 G logic_out [31:0] $end
$var wire 32 H adder_sum [31:0] $end
$var wire 1 I adder_cout $end
$var wire 1 J adder_cin $end
$var wire 32 K adder_B [31:0] $end
$var parameter 5 L OP_ADD $end
$var parameter 5 M OP_AND $end
$var parameter 5 N OP_OR $end
$var parameter 5 O OP_ROTL $end
$var parameter 5 P OP_ROTR $end
$var parameter 5 Q OP_SLL $end
$var parameter 5 R OP_SLT $end
$var parameter 5 S OP_SRA $end
$var parameter 5 T OP_SRL $end
$var parameter 5 U OP_SUB $end
$var parameter 5 V OP_XOR $end
$var reg 1 $ carryout $end
$var reg 2 W logic_sel [1:0] $end
$var reg 1 # overflow $end
$var reg 32 X result [31:0] $end
$var reg 3 Y shifter_sel [2:0] $end
$var reg 1 ! zero $end
$scope module u_logic_unit $end
$var wire 32 Z A [31:0] $end
$var wire 32 [ B [31:0] $end
$var wire 2 \ sel [1:0] $end
$var reg 32 ] Y [31:0] $end
$upscope $end
$scope module u_ripple_adder $end
$var wire 32 ^ A [31:0] $end
$var wire 32 _ B [31:0] $end
$var wire 1 J Cin $end
$var wire 32 ` carry [31:0] $end
$var wire 32 a Sum [31:0] $end
$var wire 1 I Cout $end
$scope begin fa_loop[1] $end
$var parameter 2 b i $end
$upscope $end
$scope begin fa_loop[2] $end
$var parameter 3 c i $end
$upscope $end
$scope begin fa_loop[3] $end
$var parameter 3 d i $end
$upscope $end
$scope begin fa_loop[4] $end
$var parameter 4 e i $end
$upscope $end
$scope begin fa_loop[5] $end
$var parameter 4 f i $end
$upscope $end
$scope begin fa_loop[6] $end
$var parameter 4 g i $end
$upscope $end
$scope begin fa_loop[7] $end
$var parameter 4 h i $end
$upscope $end
$scope begin fa_loop[8] $end
$var parameter 5 i i $end
$upscope $end
$scope begin fa_loop[9] $end
$var parameter 5 j i $end
$upscope $end
$scope begin fa_loop[10] $end
$var parameter 5 k i $end
$upscope $end
$scope begin fa_loop[11] $end
$var parameter 5 l i $end
$upscope $end
$scope begin fa_loop[12] $end
$var parameter 5 m i $end
$upscope $end
$scope begin fa_loop[13] $end
$var parameter 5 n i $end
$upscope $end
$scope begin fa_loop[14] $end
$var parameter 5 o i $end
$upscope $end
$scope begin fa_loop[15] $end
$var parameter 5 p i $end
$upscope $end
$scope begin fa_loop[16] $end
$var parameter 6 q i $end
$upscope $end
$scope begin fa_loop[17] $end
$var parameter 6 r i $end
$upscope $end
$scope begin fa_loop[18] $end
$var parameter 6 s i $end
$upscope $end
$scope begin fa_loop[19] $end
$var parameter 6 t i $end
$upscope $end
$scope begin fa_loop[20] $end
$var parameter 6 u i $end
$upscope $end
$scope begin fa_loop[21] $end
$var parameter 6 v i $end
$upscope $end
$scope begin fa_loop[22] $end
$var parameter 6 w i $end
$upscope $end
$scope begin fa_loop[23] $end
$var parameter 6 x i $end
$upscope $end
$scope begin fa_loop[24] $end
$var parameter 6 y i $end
$upscope $end
$scope begin fa_loop[25] $end
$var parameter 6 z i $end
$upscope $end
$scope begin fa_loop[26] $end
$var parameter 6 { i $end
$upscope $end
$scope begin fa_loop[27] $end
$var parameter 6 | i $end
$upscope $end
$scope begin fa_loop[28] $end
$var parameter 6 } i $end
$upscope $end
$scope begin fa_loop[29] $end
$var parameter 6 ~ i $end
$upscope $end
$scope begin fa_loop[30] $end
$var parameter 6 !" i $end
$upscope $end
$scope begin fa_loop[31] $end
$var parameter 6 "" i $end
$upscope $end
$upscope $end
$scope module u_shifter $end
$var wire 32 #" A [31:0] $end
$var wire 3 $" sel [2:0] $end
$var wire 5 %" shamt [4:0] $end
$var reg 32 &" Y [31:0] $end
$upscope $end
$upscope $end
$scope task apply_and_check $end
$var reg 32 '" ta [31:0] $end
$var reg 32 (" tb [31:0] $end
$var reg 1 )" tcin $end
$var reg 5 *" top [4:0] $end
$var reg 5 +" tshamt [4:0] $end
$upscope $end
$scope task expected $end
$var reg 32 ," ta [31:0] $end
$var reg 32 -" tb [31:0] $end
$var reg 1 ." tcin $end
$var reg 5 /" top [4:0] $end
$var reg 5 0" tshamt [4:0] $end
$upscope $end
$upscope $end
$enddefinitions $end
$comment Show the parameter values. $end
$dumpall
b11111 ""
b11110 !"
b11101 ~
b11100 }
b11011 |
b11010 {
b11001 z
b11000 y
b10111 x
b10110 w
b10101 v
b10100 u
b10011 t
b10010 s
b10001 r
b10000 q
b1111 p
b1110 o
b1101 n
b1100 m
b1011 l
b1010 k
b1001 j
b1000 i
b111 h
b110 g
b101 f
b100 e
b11 d
b10 c
b1 b
b100 V
b1 U
b110 T
b111 S
b1010 R
b101 Q
b1001 P
b1000 O
b11 N
b10 M
b0 L
b100 /
b1 .
b110 -
b111 ,
b1010 +
b101 *
b1001 )
b1000 (
b11 '
b10 &
b0 %
$end
#0
$dumpvars
bx 0"
bx /"
x."
bx -"
bx ,"
b0 +"
b0 *"
0)"
b1010 ("
b1111 '"
b1111 &"
b0 %"
b0 $"
b1111 #"
b11001 a
b1110 `
b1010 _
b1111 ^
b1010 ]
b0 \
b1010 [
b1111 Z
b0 Y
b11001 X
b0 W
b1010 K
0J
0I
b11001 H
b1010 G
b1111 F
b0 E
b0 D
b1010 C
b1111 B
bx A
bx @
bx ?
bx >
b0 =
bx <
b0 ;
bx :
b0 9
bx 8
b0 7
x6
bx 5
x4
x3
02
b1010 1
b1111 0
0$
0#
b11001 "
0!
$end
#5000
1!
1$
1I
b11111111111111111111111111111111 `
b0 H
b0 a
b1 K
b1 _
b1 G
b1 ]
b11111111111111111111111111111111 F
b11111111111111111111111111111111 &"
b0 "
b0 X
b1 1
b1 C
b1 [
b11111111111111111111111111111111 0
b11111111111111111111111111111111 B
b11111111111111111111111111111111 Z
b11111111111111111111111111111111 ^
b11111111111111111111111111111111 #"
b1 ("
b11111111111111111111111111111111 '"
b1 =
06
04
03
b11001 5
b0 /"
b0 0"
0."
b1010 -"
b1111 ,"
#10000
0I
1#
b10000000000000000000000000000000 "
b10000000000000000000000000000000 X
b10000000000000000000000000000000 H
b10000000000000000000000000000000 a
b1000000000000000000000000000000 `
b1000000000000000000000000000000 K
b1000000000000000000000000000000 _
b1000000000000000000000000000000 G
b1000000000000000000000000000000 ]
b1000000000000000000000000000000 F
b1000000000000000000000000000000 &"
0!
0$
b1000000000000000000000000000000 1
b1000000000000000000000000000000 C
b1000000000000000000000000000000 [
b1000000000000000000000000000000 0
b1000000000000000000000000000000 B
b1000000000000000000000000000000 Z
b1000000000000000000000000000000 ^
b1000000000000000000000000000000 #"
b1000000000000000000000000000000 ("
b1000000000000000000000000000000 '"
b10 =
16
13
b0 5
b1 -"
b11111111111111111111111111111111 ,"
#15000
1$
1I
b1111 H
b1111 a
b11111111111111111111111111110000 `
1J
b11111111111111111111111111111010 K
b11111111111111111111111111111010 _
b100 G
b100 ]
b10100 F
b10100 &"
0#
b1111 "
b1111 X
b1 7
b1 D
b101 1
b101 C
b101 [
b10100 0
b10100 B
b10100 Z
b10100 ^
b10100 #"
b1 *"
b101 ("
b10100 '"
b11 =
14
b10000000000000000000000000000000 5
06
03
b1000000000000000000000000000000 -"
b1000000000000000000000000000000 ,"
#20000
0!
0I
1#
b0 K
b0 _
b10000000000000000000000000000000 H
b10000000000000000000000000000000 a
b1111111111111111111111111111111 `
b1111111111111111111111111111111 G
b1111111111111111111111111111111 ]
b1111111111111111111111111111111 F
b1111111111111111111111111111111 &"
0$
b10000000000000000000000000000000 "
b10000000000000000000000000000000 X
b11111111111111111111111111111111 1
b11111111111111111111111111111111 C
b11111111111111111111111111111111 [
b1111111111111111111111111111111 0
b1111111111111111111111111111111 B
b1111111111111111111111111111111 Z
b1111111111111111111111111111111 ^
b1111111111111111111111111111111 #"
b11111111111111111111111111111111 ("
b1111111111111111111111111111111 '"
b100 =
13
b100000000000000000000000000001111 :
04
b1111 5
b1 /"
b101 -"
b10100 ,"
#25000
0I
b10110100101101001011010010110100 H
b10110100101101001011010010110100 a
b1111000011110000111100001111 `
b1111000011110000111100001111 K
b1111000011110000111100001111 _
0J
b101000001010000010100000101 G
b101000001010000010100000101 ]
b10100101101001011010010110100101 F
b10100101101001011010010110100101 &"
0#
b101000001010000010100000101 "
b101000001010000010100000101 X
b10 7
b10 D
b1111000011110000111100001111 1
b1111000011110000111100001111 C
b1111000011110000111100001111 [
b10100101101001011010010110100101 0
b10100101101001011010010110100101 B
b10100101101001011010010110100101 Z
b10100101101001011010010110100101 ^
b10100101101001011010010110100101 #"
b10 *"
b1111000011110000111100001111 ("
b10100101101001011010010110100101 '"
b101 =
14
b10000000000000000000000000000000 :
03
b10000000000000000000000000000000 5
b11111111111111111111111111111111 -"
b1111111111111111111111111111111 ,"
#30000
b10101111101011111010111110101111 G
b10101111101011111010111110101111 ]
b1 W
b1 \
b10101111101011111010111110101111 "
b10101111101011111010111110101111 X
b11 7
b11 D
b11 *"
b110 =
04
b101000001010000010100000101 5
b10 /"
b1111000011110000111100001111 -"
b10100101101001011010010110100101 ,"
#35000
1I
b10100101101001001010010110100101 H
b10100101101001001010010110100101 a
b11111111111111110000000000000000 `
b11111111111111110000000000000000 K
b11111111111111110000000000000000 _
b1011010010110101010010110100101 G
b1011010010110101010010110100101 ]
b10 W
b10 \
b1011010010110101010010110100101 "
b1011010010110101010010110100101 X
b100 7
b100 D
b11111111111111110000000000000000 1
b11111111111111110000000000000000 C
b11111111111111110000000000000000 [
b100 *"
b11111111111111110000000000000000 ("
b111 =
b10101111101011111010111110101111 5
b11 /"
#40000
0I
b0 `
b1111111111111111 H
b1111111111111111 a
b0 K
b0 _
b0 G
b0 ]
b111111111111111100000000 F
b111111111111111100000000 &"
b0 W
b0 \
b111111111111111100000000 "
b111111111111111100000000 X
b101 7
b101 D
b1000 9
b1000 E
b1000 %"
b0 1
b0 C
b0 [
b1111111111111111 0
b1111111111111111 B
b1111111111111111 Z
b1111111111111111 ^
b1111111111111111 #"
b101 *"
b1000 +"
b0 ("
b1111111111111111 '"
b1000 =
b1011010010110101010010110100101 5
b100 /"
b11111111111111110000000000000000 -"
#45000
b11111111000000000000000000000000 H
b11111111000000000000000000000000 a
b111111110000000000000000 F
b111111110000000000000000 &"
b1 Y
b1 $"
b111111110000000000000000 "
b111111110000000000000000 X
b110 7
b110 D
b11111111000000000000000000000000 0
b11111111000000000000000000000000 B
b11111111000000000000000000000000 Z
b11111111000000000000000000000000 ^
b11111111000000000000000000000000 #"
b110 *"
b11111111000000000000000000000000 '"
b1001 =
b111111111111111100000000 5
b101 /"
b1000 0"
b0 -"
b1111111111111111 ,"
#50000
b10000000000000000000000000000000 H
b10000000000000000000000000000000 a
b11111000000000000000000000000000 F
b11111000000000000000000000000000 &"
b10 Y
b10 $"
b11111000000000000000000000000000 "
b11111000000000000000000000000000 X
b111 7
b111 D
b100 9
b100 E
b100 %"
b10000000000000000000000000000000 0
b10000000000000000000000000000000 B
b10000000000000000000000000000000 Z
b10000000000000000000000000000000 ^
b10000000000000000000000000000000 #"
b111 *"
b100 +"
b10000000000000000000000000000000 '"
b1010 =
b111111110000000000000000 5
b110 /"
b11111111000000000000000000000000 ,"
#55000
b10010001101000101011001111000 H
b10010001101000101011001111000 a
b110100010101100111100000010010 F
b110100010101100111100000010010 &"
b11 Y
b11 $"
b110100010101100111100000010010 "
b110100010101100111100000010010 X
b1000 7
b1000 D
b1000 9
b1000 E
b1000 %"
b10010001101000101011001111000 0
b10010001101000101011001111000 B
b10010001101000101011001111000 Z
b10010001101000101011001111000 ^
b10010001101000101011001111000 #"
b1000 *"
b1000 +"
b10010001101000101011001111000 '"
b1011 =
b11111000000000000000000000000000 5
b111 /"
b100 0"
b10000000000000000000000000000000 ,"
#60000
b1111000000100100011010001010110 F
b1111000000100100011010001010110 &"
b100 Y
b100 $"
b1111000000100100011010001010110 "
b1111000000100100011010001010110 X
b1001 7
b1001 D
b1001 *"
b1100 =
b10010001101000101011001111000 ?
b1000 >
b110100010101100111100000010010 5
b1000 /"
b1000 0"
b10010001101000101011001111000 ,"
#65000
1I
b11111111111111111111111111111111 `
b0 H
b0 a
b1 K
b1 _
b1 G
b1 ]
b11111111111111111111111111111111 F
b11111111111111111111111111111111 &"
b0 Y
b0 $"
b1 "
b1 X
b1010 7
b1010 D
b0 9
b0 E
b0 %"
b1 1
b1 C
b1 [
b11111111111111111111111111111111 0
b11111111111111111111111111111111 B
b11111111111111111111111111111111 Z
b11111111111111111111111111111111 ^
b11111111111111111111111111111111 #"
b1010 *"
b0 +"
b1 ("
b11111111111111111111111111111111 '"
b1101 =
b10010001101000101011001111000 A
b1000 @
b1111000000100100011010001010110 5
b1001 /"
#70000
0I
0#
b0 H
b0 a
b0 `
b0 K
b0 _
b0 G
b0 ]
b0 F
b0 &"
1!
0$
b0 "
b0 X
b0 7
b0 D
b0 1
b0 C
b0 [
b0 0
b0 B
b0 Z
b0 ^
b0 #"
b0 *"
b0 ("
b0 '"
b1110 =
b1 5
b1010 /"
b0 0"
b1 -"
b11111111111111111111111111111111 ,"
#75000
1$
1I
b111100000001001000100001111000 "
b111100000001001000100001111000 X
b11000011111110110111111110000111 `
b111100000001001000100001111000 H
b111100000001001000100001111000 a
1J
b1111011011110110010100111110110 K
b1111011011110110010100111110110 _
b10000000100000000101011000000001 G
b10000000100000000101011000000001 ]
b1000100101011110100000010000 F
b1000100101011110100000010000 &"
0!
b1 7
b1 D
b100 9
b100 E
b100 %"
b10000100100001001101011000001001 1
b10000100100001001101011000001001 C
b10000100100001001101011000001001 [
b11000000100010010101111010000001 0
b11000000100010010101111010000001 B
b11000000100010010101111010000001 Z
b11000000100010010101111010000001 ^
b11000000100010010101111010000001 #"
b1 *"
b100 +"
b10000100100001001101011000001001 ("
b11000000100010010101111010000001 '"
b10010000101010011010100100100 8
b0 <
b1111 =
16
b0 5
b0 /"
b0 -"
b0 ,"
#80000
b10000 =
b111100000001001000100001111000 5
13
b100111100000001001000100001111000 :
06
b1 /"
b100 0"
b10000100100001001101011000001001 -"
b11000000100010010101111010000001 ,"
#90000
0I
b1001101100110010001010010011011 H
b1001101100110010001010010011011 a
b110111111111111101100001101 `
b1000110110111111001100110001101 K
b1000110110111111001100110001101 _
b1000110111111111111101110001101 G
b1000110111111111111101110001101 ]
b110101110010111101100001101000 F
b110101110010111101100001101000 &"
b1 W
b1 \
0$
b1000110111111111111101110001101 "
b1000110111111111111101110001101 X
b11 7
b11 D
b11 9
b11 E
b11 %"
12
b1000110110111111001100110001101 1
b1000110110111111001100110001101 C
b1000110110111111001100110001101 [
b110101110010111101100001101 0
b110101110010111101100001101 B
b110101110010111101100001101 Z
b110101110010111101100001101 ^
b110101110010111101100001101 #"
b11 *"
b11 +"
1)"
b1000110110111111001100110001101 ("
b110101110010111101100001101 '"
b10110001111100000101011001100011 8
b1 <
#95000
b10001 =
03
b1000110111111111111101110001101 5
b11 /"
b11 0"
1."
b1000110110111111001100110001101 -"
b110101110010111101100001101 ,"
#105000
b111101111100111100000001 `
b111110010111011000000001110 H
b111110010111011000000001110 a
0J
b110110101111100110100001101 K
b110110101111100110100001101 _
b110111101111110111100001101 G
b110111101111110111100001101 ]
b10001100000001000000000000000000 F
b10001100000001000000000000000000 &"
b1 W
b1 \
b110111101111110111100001101 "
b110111101111110111100001101 X
b10010 9
b10010 E
b10010 %"
02
b110110101111100110100001101 1
b110110101111100110100001101 C
b110110101111100110100001101 [
b111100111110001100000001 0
b111100111110001100000001 B
b111100111110001100000001 Z
b111100111110001100000001 ^
b111100111110001100000001 #"
b10010 +"
0)"
b110110101111100110100001101 ("
b111100111110001100000001 '"
b10001001001101110101001000010010 8
b10 <
#110000
b10010 =
b110111101111110111100001101 5
b10010 0"
0."
b110110101111100110100001101 -"
b111100111110001100000001 ,"
#120000
b1000110111111011111011110001101 `
b10111101000000100100111101111010 H
b10111101000000100100111101111010 a
1J
b1000110001011011111011110001100 K
b1000110001011011111011110001100 _
b1000110000001000101011110001100 G
b1000110000001000101011110001100 ]
b10100000000000000000000000000000 F
b10100000000000000000000000000000 &"
b0 W
b0 \
b10100000000000000000000000000000 "
b10100000000000000000000000000000 X
b101 7
b101 D
b11101 9
b11101 E
b11101 %"
12
b1000110001011011111011110001100 1
b1000110001011011111011110001100 C
b1000110001011011111011110001100 [
b1110110110101000101011111101101 0
b1110110110101000101011111101101 B
b1110110110101000101011111101101 Z
b1110110110101000101011111101101 ^
b1110110110101000101011111101101 #"
b101 *"
b11101 +"
1)"
b1000110001011011111011110001100 ("
b1110110110101000101011111101101 '"
b11110100011011100110100111101 8
b11 <
#125000
b10011 =
b10100000000000000000000000000000 5
b101 /"
b11101 0"
1."
b1000110001011011111011110001100 -"
b1110110110101000101011111101101 ,"
#135000
0#
1$
1I
b10111000000010110101011101110000 H
b10111000000010110101011101110000 a
b11000111111101111000000010001111 `
b11010101000100111101001010101010 K
b11010101000100111101001010101010 _
b11000000000100111000000010000000 G
b11000000000100111000000010000000 ]
b10111101111000010011000101000000 F
b10111101111000010011000101000000 &"
b10111000000010110101011101110000 "
b10111000000010110101011101110000 X
b0 7
b0 D
b110 9
b110 E
b110 %"
b11010101000100111101001010101010 1
b11010101000100111101001010101010 C
b11010101000100111101001010101010 [
b11100010111101111000010011000101 0
b11100010111101111000010011000101 B
b11100010111101111000010011000101 Z
b11100010111101111000010011000101 ^
b11100010111101111000010011000101 #"
b0 *"
b110 +"
b11010101000100111101001010101010 ("
b11100010111101111000010011000101 '"
b11100011001101110010010011000110 8
b100 <
#140000
b10100 =
13
b10111000000010110101011101110000 5
b0 /"
b110 0"
b11010101000100111101001010101010 -"
b11100010111101111000010011000101 ,"
